control_error_handler/__init__.py
control_error_handler/error_handler.py
control_error_handler/exceptions.py
control_error_handler-0.1.3.dist-info/LICENSE
control_error_handler-0.1.3.dist-info/METADATA
control_error_handler-0.1.3.dist-info/WHEEL
control_error_handler-0.1.3.dist-info/top_level.txt
control_error_handler-0.1.3.dist-info/RECORD
