Metadata-Version: 2.1
Name: control-error-handler
Version: 0.1.3
Summary: Error handler for flask with sending exceptions to control service.
Home-page: UNKNOWN
Author: 54origins
Author-email: opensource@54origins.com
License: MIT
Keywords: flask,control service,exception,error_handler,54origins
Platform: UNKNOWN
Classifier: Development Status :: 3 - Alpha
Classifier: License :: OSI Approved :: MIT License
Classifier: Programming Language :: Python :: 3.7
Requires-Python: >=3.0, !=3.0.*, !=3.1.*, !=3.2.*, !=3.3.*, !=3.3.*, !=3.4.*, !=3.6.*
Requires-Dist: flask (>=1.0)
Requires-Dist: requests (>=2.22.0)
